yelp_uri/__init__.py
yelp_uri/_urlparse_less_special.py
yelp_uri/encoding.py
yelp_uri/search.py
yelp_uri/urllib_utf8.py
yelp_uri/tlds/__init__.py
yelp_uri/tlds/all.py
yelp_uri/tlds/common.py
yelp_uri-2.0.1.dist-info/METADATA
yelp_uri-2.0.1.dist-info/WHEEL
yelp_uri-2.0.1.dist-info/top_level.txt
yelp_uri-2.0.1.dist-info/RECORD
