Metadata-Version: 2.1
Name: yelp-uri
Version: 2.0.1
Summary: Uri utilities maintained by Yelp
Home-page: https://github.com/Yelp/yelp_uri
Author: Buck Golemon
Author-email: buck@yelp.com
Platform: all
Classifier: License :: Public Domain
Classifier: Programming Language :: Python :: 3.8
Requires-Dist: yelp-encodings
Requires-Dist: yelp-bytes
